ffysh/__init__.py
ffysh/__main__.py
ffysh/cli.py
ffysh/modules/__init__.py
ffysh/modules/asset/asset.py
ffysh/modules/asset/image.py
ffysh/modules/asset/text.py
ffysh/modules/cache/test.py
ffysh/modules/cli/base.py
ffysh/modules/dataset/dataset.py
ffysh/modules/ffysh_pytorch.py
ffysh/modules/internals/api.py
ffysh/modules/internals/authorization.py
ffysh/modules/internals/errors.py
ffysh/modules/internals/file.py
ffysh/modules/internals/project.py
ffysh/modules/pytorch/ffysh_dataset.py
ffysh/modules/pytorch/image_dataset.py
ffysh/modules/stream/stream.py
ffysh/modules/utils/config.py
ffysh/modules/utils/imports.py
fysh-0.0.1.9.dist-info/METADATA
fysh-0.0.1.9.dist-info/WHEEL
fysh-0.0.1.9.dist-info/entry_points.txt
fysh-0.0.1.9.dist-info/RECORD
